{
  "url": "https://carelabz.com/ph/category/harmonic-study-analysis/",
  "slug": "harmonic-study-analysis",
  "pageType": "blog",
  "metaTitle": "Harmonic Study & Analysis Archives - Carelabs Philippines",
  "metaDescription": "",
  "canonicalSource": "",
  "h1": "",
  "h2": [
    "Philippine Power System Harmonic Analysis",
    "Why is Harmonic Analysis and Study So Important for Philippine Businesses?"
  ],
  "h3": [],
  "paragraphs": [
    "In the present world, power is an essential part of daily life. Most daily-use things are powered in some form. To provide people with electricity in a safe and reasonable manner, we must use the most advanced power technologies available. Harmonics increase the RMS of the circuit’s current flow, hence increasing the loss. This has…",
    "Harmonics is an integral part of a power system since it affects the quality of the electricity and how things function. High harmonic levels can cause equipment components to overheat and shorten their lifespan. Pure sine waves created by a perfect power source are modified by harmonics. Harmonic distortion hinders a company’s ability to create…"
  ],
  "bulletLists": [],
  "wordCount": 132,
  "phones": [],
  "emails": [],
  "scrapedAt": "2026-04-21T18:06:17Z"
}